{"name":"neuronsSendOutValueBetweenZeroAndOne","id":"com.example.neuralnet.domain.BasicNeuronModelTest:neuronsSendOutValueBetweenZeroAndOne","testCaseName":"com.example.neuralnet.domain.BasicNeuronModelTest","testSteps":[{"number":1,"description":"Tester watch neuron output","duration":0,"startTime":"2021-12-05T23:39:30.150115+01:00[Europe/Berlin]","result":"SUCCESS","precondition":false,"level":0},{"number":2,"description":"Tester send signal to neuron","duration":2,"startTime":"2021-12-05T23:39:30.152947+01:00[Europe/Berlin]","result":"SUCCESS","precondition":false,"level":0,"children":[{"number":3,"description":"send Signal(source\u003dWire{uuid\u003d341be4bc-3d47-4670-8ff6-c2dda6a96b57}, strength\u003d0.5) from Wire{uuid\u003d341be4bc-3d47-4670-8ff6-c2dda6a96b57} to Neuron\u003cb5f90765-4f9c-440e-ac10-df0c06ef29fe\u003e","duration":0,"startTime":"2021-12-05T23:39:30.153353+01:00[Europe/Berlin]","result":"SUCCESS","precondition":false,"level":1}]},{"number":4,"description":"Then Latest Neuron Output should be a numeric value within (0.5) of (0.5)","duration":1,"startTime":"2021-12-05T23:39:30.156975+01:00[Europe/Berlin]","result":"SUCCESS","precondition":false,"level":0}],"userStory":{"id":"com.example.neuralnet.domain.BasicNeuronModelTest","storyName":"Basic neuron model test","displayName":"Basic neuron model test","storyClassName":"com.example.neuralnet.domain.BasicNeuronModelTest","path":"com.example.neuralnet.domain","type":"story"},"featureTag":{"name":"Domain/Basic neuron model test","type":"story","displayName":"Domain/Basic neuron model test"},"title":"Neurons send out value between zero and one","tags":[{"name":"Domain/Basic neuron model test","type":"story","displayName":"Domain/Basic neuron model test"}],"startTime":"2021-12-05T23:39:30.142742+01:00[Europe/Berlin]","duration":16,"projectKey":"","driver":"","isManualTestingUpToDate":false,"manual":false,"testSource":"JUnit","actors":[{"name":"tester","can":["Interact With Neuron"]}],"order":0,"result":"SUCCESS"}