{"name":"whenAcceptingAnInputTheSigmoidFunctionIsAppliedAndSentToTheOutput","id":"com.example.e2e.neuralnet.integration.NeuronIT:whenAcceptingAnInputTheSigmoidFunctionIsAppliedAndSentToTheOutput","testCaseName":"com.example.e2e.neuralnet.integration.NeuronIT","testSteps":[{"number":1,"description":"Tester setup mocked neuron implementation","duration":21,"startTime":"2021-12-10T00:01:04.445100+01:00[Europe/Berlin]","result":"SUCCESS","precondition":false,"level":0},{"number":2,"description":"Tester apply an input to spy neuron","duration":9,"startTime":"2021-12-10T00:01:04.489825+01:00[Europe/Berlin]","result":"SUCCESS","precondition":false,"level":0},{"number":3,"description":"Then Sigmoid Function Is Invoked","duration":10,"startTime":"2021-12-10T00:01:04.501135+01:00[Europe/Berlin]","result":"SUCCESS","precondition":false,"level":0},{"number":4,"description":"Then Output Is Propagated","duration":3,"startTime":"2021-12-10T00:01:04.513234+01:00[Europe/Berlin]","result":"SUCCESS","precondition":false,"level":0}],"userStory":{"id":"com.example.e2e.neuralnet.integration.NeuronIT","storyName":"Neuron IT","displayName":"Neuron IT","storyClassName":"com.example.e2e.neuralnet.integration.NeuronIT","path":"neuralnet.integration","type":"story"},"featureTag":{"name":"Integration/Neuron IT","type":"story","displayName":"Integration/Neuron IT"},"title":"When accepting an input the sigmoid function is applied and sent to the output","tags":[{"name":"Neuralnet/Integration","type":"feature","displayName":"Integration"},{"name":"Neuralnet","type":"capability","displayName":"Neuralnet"},{"name":"Integration/Neuron IT","type":"story","displayName":"Integration/Neuron IT"}],"startTime":"2021-12-10T00:01:04.215085+01:00[Europe/Berlin]","duration":304,"projectKey":"","driver":"","isManualTestingUpToDate":false,"manual":false,"testSource":"JUnit","actors":[{"name":"tester","can":["Interact With Neuron","Spy On Neuron"]}],"order":0,"result":"SUCCESS"}