{"name":"neuronsAcceptsMultipleInputs","id":"com.example.neuralnet.domain.BasicNeuronModelTest:neuronsAcceptsMultipleInputs","testCaseName":"com.example.neuralnet.domain.BasicNeuronModelTest","testSteps":[{"number":1,"description":"Then a neuron accepts inputs","duration":2,"startTime":"2021-12-04T01:02:43.369528+01:00[Europe/Berlin]","result":"SUCCESS","precondition":false,"level":0}],"userStory":{"id":"com.example.neuralnet.domain.BasicNeuronModelTest","storyName":"Basic neuron model test","displayName":"Basic neuron model test","storyClassName":"com.example.neuralnet.domain.BasicNeuronModelTest","path":"com.example.neuralnet.domain","type":"story"},"featureTag":{"name":"Domain/Basic neuron model test","type":"story","displayName":"Domain/Basic neuron model test"},"title":"Neurons accepts multiple inputs","tags":[{"name":"Domain/Basic neuron model test","type":"story","displayName":"Domain/Basic neuron model test"}],"startTime":"2021-12-04T01:02:43.355629+01:00[Europe/Berlin]","duration":33,"projectKey":"","driver":"","isManualTestingUpToDate":false,"manual":false,"testSource":"JUnit","actors":[{"name":"tester","can":["Interact With Neuron"]}],"order":0,"result":"SUCCESS"}